{
  "project_info": {
    "project_number": "160645220973",
    "project_id": "efep-be",
    "storage_bucket": "efep-be.firebasestorage.app"
  },
  "client": [
    {
      "client_info": {
        "mobilesdk_app_id": "1:160645220973:android:7f57674804634ca48c0d64",
        "android_client_info": {
          "package_name": "com.example.efep_chat"
        }
      },
      "oauth_client": [],
      "api_key": [
        {
          "current_key": "AIzaSyCESpJq8dxwh_tuzYS53SOgUMcE8t-69J8"
        }
      ],
      "services": {
        "appinvite_service": {
          "other_platform_oauth_client": []
        }
      }
    }
  ],
  "configuration_version": "1"
}